obvyr_cli/__init__.py
obvyr_cli/api_client.py
obvyr_cli/archive_builder.py
obvyr_cli/cli.py
obvyr_cli/command_wrapper.py
obvyr_cli/config.py
obvyr_cli/error_handling.py
obvyr_cli/logging_config.py
obvyr_cli/schemas.py
obvyr_cli/utils.py
obvyr_cli-2.3.0.dist-info/METADATA
obvyr_cli-2.3.0.dist-info/WHEEL
obvyr_cli-2.3.0.dist-info/entry_points.txt
obvyr_cli-2.3.0.dist-info/RECORD
